setup.py
rmqid/__init__.py
rmqid/base.py
rmqid/channel.py
rmqid/connection.py
rmqid/exceptions.py
rmqid/exchange.py
rmqid/message.py
rmqid/queue.py
rmqid/simple.py
rmqid/tx.py
rmqid/utils.py
rmqid.egg-info/PKG-INFO
rmqid.egg-info/SOURCES.txt
rmqid.egg-info/dependency_links.txt
rmqid.egg-info/requires.txt
rmqid.egg-info/top_level.txt
rmqid.egg-info/zip-safe