Metadata-Version: 1.0
Name: rmqid
Version: 0.4.3
Summary: A minimalistic & pythonic AMQP library focused on supporting RabbitMQ
Home-page: http://github.com/gmr/rmqid
Author: Gavin M. Roy
Author-email: gavinmroy@gmail.com
License: BSD
Platform: UNKNOWN
Classifier: Development Status :: 3 - Alpha
Classifier: Intended Audience :: Developers
Classifier: License :: OSI Approved :: BSD License
Classifier: Operating System :: OS Independent
Classifier: Programming Language :: Python :: 2.6
Classifier: Programming Language :: Python :: 2.7
Classifier: Programming Language :: Python :: 3.3
Classifier: Topic :: Communications
Classifier: Topic :: Internet
Classifier: Topic :: Software Development :: Libraries
